{"compressionlevel": -1, "height": 15, "infinite": false, "layers": [{"data": [0, 0, 0, 0, 0, 71, 0, 0, 0, 0, 0, 0, 0, 0, 0, 71, 0, 0, 0, 0, 0, 0, 0, 0, 0, 0, 0, 0, 0, 0, 71, 0, 0, 0, 0, 0, 0, 0, 0, 0, 0, 71, 71, 72, 71, 71, 72, 71, 71, 72, 71, 71, 72, 71, 71, 72, 71, 71, 72, 0, 0, 71, 71, 72, 71, 71, 72, 71, 71, 72, 71, 71, 72, 71, 71, 72, 71, 71, 72, 0, 0, 71, 71, 72, 71, 71, 72, 71, 71, 72, 71, 71, 72, 71, 71, 72, 71, 71, 72, 0, 0, 0, 0, 0, 0, 71, 71, 0, 0, 0, 0, 0, 0, 0, 71, 71, 0, 0, 0, 0, 0, 71, 71, 71, 71, 71, 71, 71, 71, 71, 71, 71, 71, 71, 71, 71, 71, 71, 71, 0, 0, 71, 21, 21, 21, 71, 71, 71, 71, 71, 71, 71, 71, 71, 71, 71, 71, 71, 71, 0, 0, 71, 71, 71, 71, 71, 71, 71, 71, 71, 71, 71, 71, 71, 71, 71, 71, 71, 71, 0, 0, 71, 21, 21, 71, 71, 71, 71, 71, 71, 71, 71, 71, 71, 71, 71, 71, 71, 71, 0, 0, 71, 71, 71, 71, 71, 71, 71, 71, 71, 71, 71, 71, 71, 71, 71, 71, 71, 71, 0, 0, 71, 21, 21, 71, 71, 71, 71, 71, 71, 71, 71, 71, 71, 71, 71, 71, 71, 71, 0, 0, 71, 71, 71, 71, 71, 71, 71, 71, 71, 71, 71, 71, 71, 71, 71, 71, 71, 71, 0, 0, 71, 71, 71, 71, 71, 71, 71, 71, 71, 71, 71, 71, 71, 71, 71, 71, 71, 71, 0, 0, 0, 0, 71, 0, 0, 0, 0, 0, 0, 71, 0, 0, 0, 0, 0, 0, 0, 0, 0], "height": 15, "id": 1, "name": "Ground", "opacity": 1, "type": "tilelayer", "visible": true, "width": 20, "x": 0, "y": 0}, {"data": [1, 1, 1, 1, 1, 10, 1, 1, 1, 1, 1, 1, 1, 1, 1, 10, 1, 1, 1, 1, 1, 1, 1, 1, 1, 1, 1, 1, 1, 1, 13, 1, 1, 1, 1, 1, 1, 1, 1, 1, 1, 1, 1, 1, 1, 1, 1, 1, 1, 1, 1, 1, 1, 1, 1, 1, 1, 1, 1, 1, 1, 1, 1, 1, 1, 1, 1, 1, 1, 1, 1, 1, 1, 1, 1, 1, 1, 1, 1, 1, 1, 1, 1, 1, 1, 1, 1, 1, 1, 1, 1, 1, 1, 1, 1, 1, 1, 1, 1, 1, 1, 1, 1, 1, 1, 1, 1, 1, 1, 1, 1, 1, 1, 1, 1, 1, 1, 1, 1, 1, 1, 1, 1, 1, 1, 1, 1, 1, 1, 1, 1, 1, 1, 1, 1, 1, 1, 1, 1, 1, 1, 1, 1, 1, 1, 1, 1, 1, 1, 1, 1, 1, 1, 1, 1, 1, 1, 1, 1, 1, 1, 1, 22, 22, 22, 1, 1, 1, 1, 1, 1, 1, 1, 1, 1, 1, 1, 1, 1, 1, 1, 1, 1, 1, 1, 1, 1, 1, 1, 1, 1, 1, 1, 1, 1, 1, 1, 1, 1, 1, 1, 1, 22, 22, 1, 1, 1, 1, 1, 1, 1, 1, 1, 1, 1, 1, 1, 1, 1, 1, 1, 1, 1, 1, 1, 1, 1, 1, 1, 1, 1, 1, 1, 1, 1, 1, 1, 1, 1, 1, 1, 1, 22, 22, 1, 1, 1, 1, 1, 1, 1, 1, 1, 1, 1, 1, 1, 1, 1, 1, 1, 1, 1, 1, 1, 1, 1, 1, 1, 1, 1, 1, 1, 1, 1, 1, 1, 1, 1, 1, 1, 1, 1, 10, 1, 1, 1, 1, 1, 1, 10, 1, 1, 1, 1, 1, 1, 1, 1, 1], "height": 15, "id": 2, "name": "Objects", "opacity": 1, "type": "tilelayer", "visible": true, "width": 20, "x": 0, "y": 0}], "nextlayerid": 3, "nextobjectid": 1, "orientation": "orthogonal", "renderorder": "right-down", "tiledversion": "1.10.1", "tileheight": 32, "tilesets": [{"columns": 5, "firstgid": 1, "image": "../sprites/tileset.png", "imageheight": 608, "imagewidth": 160, "margin": 0, "name": "tileset", "spacing": 0, "tilecount": 93, "tileheight": 32, "tilewidth": 32}], "tilewidth": 32, "type": "map", "version": "1.10", "width": 20}